{"box_data": [{"position": {"minX": 321.0, "minY": 66.625, "maxX": 351.0, "maxY": 81.625}, "class_id": 5, "box_caption": "starfish 0.890", "scores": {"class_score": 0.89013671875}, "domain": "pixel"}, {"position": {"minX": 311.5, "minY": 90.125, "maxX": 329.5, "maxY": 108.5}, "class_id": 5, "box_caption": "starfish 0.876", "scores": {"class_score": 0.87646484375}, "domain": "pixel"}, {"position": {"minX": 274.75, "minY": 216.75, "maxX": 300.75, "maxY": 236.0}, "class_id": 0, "box_caption": "crab 0.845", "scores": {"class_score": 0.8447265625}, "domain": "pixel"}, {"position": {"minX": 406.0, "minY": 359.5, "maxX": 424.5, "maxY": 371.5}, "class_id": 0, "box_caption": "crab 0.304", "scores": {"class_score": 0.303955078125}, "domain": "pixel"}, {"position": {"minX": 354.5, "minY": 314.0, "maxX": 372.5, "maxY": 327.0}, "class_id": 5, "box_caption": "starfish 0.005", "scores": {"class_score": 0.00469970703125}, "domain": "pixel"}, {"position": {"minX": 402.5, "minY": 357.75, "maxX": 423.5, "maxY": 371.25}, "class_id": 0, "box_caption": "crab 0.004", "scores": {"class_score": 0.004314422607421875}, "domain": "pixel"}, {"position": {"minX": 403.0, "minY": 363.0, "maxX": 425.0, "maxY": 386.0}, "class_id": 0, "box_caption": "crab 0.002", "scores": {"class_score": 0.001987457275390625}, "domain": "pixel"}, {"position": {"minX": 428.25, "minY": 370.5, "maxX": 478.75, "maxY": 385.5}, "class_id": 1, "box_caption": "fish 0.001", "scores": {"class_score": 0.0011205673217773438}, "domain": "pixel"}], "class_labels": {"0": "crab", "1": "fish", "2": "jellyfish", "3": "shrimp", "4": "small_fish", "5": "starfish"}}