{"box_data": [{"position": {"minX": 320.75, "minY": 67.0625, "maxX": 350.25, "maxY": 82.1875}, "class_id": 5, "box_caption": "starfish 0.900", "scores": {"class_score": 0.89990234375}, "domain": "pixel"}, {"position": {"minX": 311.5, "minY": 89.875, "maxX": 329.5, "maxY": 108.125}, "class_id": 5, "box_caption": "starfish 0.891", "scores": {"class_score": 0.89111328125}, "domain": "pixel"}, {"position": {"minX": 275.5, "minY": 216.375, "maxX": 303.5, "maxY": 236.125}, "class_id": 0, "box_caption": "crab 0.891", "scores": {"class_score": 0.89111328125}, "domain": "pixel"}, {"position": {"minX": 405.5, "minY": 358.5, "maxX": 424.5, "maxY": 371.5}, "class_id": 0, "box_caption": "crab 0.732", "scores": {"class_score": 0.732421875}, "domain": "pixel"}, {"position": {"minX": 416.5, "minY": 196.5, "maxX": 434.5, "maxY": 207.5}, "class_id": 4, "box_caption": "small_fish 0.005", "scores": {"class_score": 0.00464630126953125}, "domain": "pixel"}, {"position": {"minX": 410.5, "minY": 362.5, "maxX": 442.5, "maxY": 385.5}, "class_id": 0, "box_caption": "crab 0.001", "scores": {"class_score": 0.00127410888671875}, "domain": "pixel"}], "class_labels": {"0": "crab", "1": "fish", "2": "jellyfish", "3": "shrimp", "4": "small_fish", "5": "starfish"}}